LICENSE
README.md
pathwin.py
setup.py
pathwin.egg-info/PKG-INFO
pathwin.egg-info/SOURCES.txt
pathwin.egg-info/dependency_links.txt
pathwin.egg-info/top_level.txt