Metadata-Version: 2.1
Name: pathwin
Version: 1.0.1
Summary: setPath is a library for easy manipulation of the Windows environment variable Path.
Home-page: https://github.com/kurages/pathwin
Author: kurages
Author-email: git.kurages@outlook.jp
License: MIT License
Platform: UNKNOWN
Classifier: Development Status :: 5 - Production/Stable
Classifier: Programming Language :: Python :: 2
Classifier: Programming Language :: Python :: 3
Classifier: Intended Audience :: Developers
Classifier: License :: OSI Approved :: MIT License
Classifier: Topic :: Software Development :: Libraries
Classifier: Topic :: Utilities
Requires-Python: >=3.6
License-File: LICENSE
